versions/__init__.py
versions/versions.py
versions_kaneryu-1.0.1.dist-info/METADATA
versions_kaneryu-1.0.1.dist-info/WHEEL
versions_kaneryu-1.0.1.dist-info/licenses/LICENSE
versions_kaneryu-1.0.1.dist-info/RECORD
