Metadata-Version: 2.3
Name: versions_kaneryu
Version: 1.0.1
Summary: Simple version class
Project-URL: Homepage, https://github.com/kaneryu/versions
Project-URL: Issues, https://github.com/kaneryu/versions/issues
Author-email: Kaneryu <hello@kan.moe>
License-File: LICENSE
Classifier: License :: OSI Approved :: MIT License
Classifier: Operating System :: OS Independent
Classifier: Programming Language :: Python :: 3
Requires-Python: >=3.8
